predictioner/__init__.py
predictioner-1.0.0.dist-info/METADATA
predictioner-1.0.0.dist-info/WHEEL
predictioner-1.0.0.dist-info/top_level.txt
predictioner-1.0.0.dist-info/RECORD
