Metadata-Version: 2.1
Name: predictioner
Version: 1.0.0
Summary: The module of the program "Predictioner"
Home-page: UNKNOWN
Author: Marco Vidali
Author-email: <vidali.marco@protonmail.com>
License: UNKNOWN
Keywords: prediction,predictioner,sequence,math,algebra,geometry,arithmetic,neural networks,ai,artificial intelligence
Platform: UNKNOWN
Classifier: Programming Language :: Python :: 3
Classifier: Operating System :: Unix
Classifier: Operating System :: MacOS :: MacOS X
Classifier: Operating System :: Microsoft :: Windows
Requires-Dist: matplotlib
Requires-Dist: numpy
Requires-Dist: tabulate
Requires-Dist: tensorflow
